orwell/__init__.py
orwell/consts.py
orwell/helper.py
orwell/metric.py
orwell/metrics_factory.py
orwell/runner.py
orwell/translator.py
orwell_translators-1.1.5.dist-info/METADATA
orwell_translators-1.1.5.dist-info/WHEEL
orwell_translators-1.1.5.dist-info/top_level.txt
orwell_translators-1.1.5.dist-info/RECORD
