Metadata-Version: 2.1
Name: orwell-translators
Version: 1.1.5
Summary: Create translators for the Orwell platform
Home-page: https://orwellmonitoring.github.io/
Author: Orwell
License: MIT
Classifier: License :: OSI Approved :: MIT License
Classifier: Programming Language :: Python :: 3
Classifier: Programming Language :: Python :: 3.7
Requires-Dist: flask
Requires-Dist: kafka-python
Requires-Dist: redis
